babeldoc/__init__.py
babeldoc/const.py
babeldoc/glossary.py
babeldoc/main.py
babeldoc/progress_monitor.py
babeldoc/assets/assets.py
babeldoc/assets/embedding_assets_metadata.py
babeldoc/asynchronize/__init__.py
babeldoc/babeldoc_exception/BabelDOCException.py
babeldoc/babeldoc_exception/__init__.py
babeldoc/docvision/README.md
babeldoc/docvision/__init__.py
babeldoc/docvision/base_doclayout.py
babeldoc/docvision/doclayout.py
babeldoc/docvision/rpc_doclayout.py
babeldoc/docvision/rpc_doclayout2.py
babeldoc/docvision/rpc_doclayout3.py
babeldoc/docvision/rpc_doclayout4.py
babeldoc/docvision/rpc_doclayout5.py
babeldoc/docvision/rpc_doclayout6.py
babeldoc/docvision/rpc_doclayout7.py
babeldoc/docvision/table_detection/rapidocr.py
babeldoc/format/__init__.py
babeldoc/format/pdf/__init__.py
babeldoc/format/pdf/converter.py
babeldoc/format/pdf/high_level.py
babeldoc/format/pdf/pdfinterp.py
babeldoc/format/pdf/result_merger.py
babeldoc/format/pdf/split_manager.py
babeldoc/format/pdf/translation_config.py
babeldoc/format/pdf/babelpdf/base14.py
babeldoc/format/pdf/babelpdf/cidfont.py
babeldoc/format/pdf/babelpdf/encoding.py
babeldoc/format/pdf/babelpdf/utils.py
babeldoc/format/pdf/babelpdf/win_core.py
babeldoc/format/pdf/document_il/__init__.py
babeldoc/format/pdf/document_il/il_version_1.py
babeldoc/format/pdf/document_il/il_version_1.rnc
babeldoc/format/pdf/document_il/il_version_1.rng
babeldoc/format/pdf/document_il/il_version_1.xsd
babeldoc/format/pdf/document_il/xml_converter.py
babeldoc/format/pdf/document_il/backend/__init__.py
babeldoc/format/pdf/document_il/backend/pdf_creater.py
babeldoc/format/pdf/document_il/frontend/__init__.py
babeldoc/format/pdf/document_il/frontend/il_creater.py
babeldoc/format/pdf/document_il/midend/__init__.py
babeldoc/format/pdf/document_il/midend/add_debug_information.py
babeldoc/format/pdf/document_il/midend/automatic_term_extractor.py
babeldoc/format/pdf/document_il/midend/detect_scanned_file.py
babeldoc-0.5.18.dist-info/METADATA
babeldoc-0.5.18.dist-info/WHEEL
babeldoc-0.5.18.dist-info/entry_points.txt
babeldoc-0.5.18.dist-info/licenses/LICENSE
babeldoc-0.5.18.dist-info/RECORD
