Metadata-Version: 2.4
Name: BabelDOC
Version: 0.5.18
Summary: Yet Another Document Translator
Project-URL: Homepage, https://github.com/funstory-ai/BabelDOC
Project-URL: Issues, https://github.com/funstory-ai/BabelDOC/issues
Author-email: awwaawwa <aw@funstory.ai>
Maintainer-email: awwaawwa <aw@funstory.ai>
License-Expression: AGPL-3.0
License-File: LICENSE
Keywords: PDF
Classifier: Operating System :: OS Independent
Classifier: Programming Language :: Python :: 3
Requires-Python: <3.14,>=3.10
Requires-Dist: bitstring>=4.3.0
Requires-Dist: chardet>=5.2.0
Requires-Dist: charset-normalizer>=2.0.0
Requires-Dist: configargparse>=1.7
Requires-Dist: cryptography>=36.0.0
Requires-Dist: freetype-py>=2.5.1
Requires-Dist: httpx[socks]>=0.27.0
Requires-Dist: huggingface-hub>=0.27.0
Requires-Dist: hyperscan>=0.7.13
Requires-Dist: msgpack>=1.1.0
Requires-Dist: numpy>=2.0.2
Requires-Dist: onnx>=1.18.0
Requires-Dist: onnxruntime>=1.16.1
Requires-Dist: openai>=1.59.3
Requires-Dist: opencv-python-headless>=4.10.0.84
Requires-Dist: orjson>=3.10.14
Requires-Dist: peewee>=3.17.8
Requires-Dist: psutil>=7.0.0
Requires-Dist: pydantic>=2.10.6
Requires-Dist: pymupdf>=1.25.1
Requires-Dist: python-levenshtein>=0.27.1
Requires-Dist: pyzstd>=0.17.0
Requires-Dist: rapidocr-onnxruntime>=1.4.4
Requires-Dist: rich>=13.9.4
Requires-Dist: rtree>=1.4.0
Requires-Dist: scikit-image>=0.25.2
Requires-Dist: scikit-learn>=1.7.1
Requires-Dist: scipy>=1.15.3
Requires-Dist: tenacity>=9.0.0
Requires-Dist: tiktoken>=0.9.0
Requires-Dist: toml>=0.10.2
Requires-Dist: tqdm>=4.67.1
Requires-Dist: uharfbuzz>=0.50.2
Requires-Dist: xsdata[cli,lxml,soap]>=24.12
Provides-Extra: cuda
Requires-Dist: onnxruntime-gpu>=1.16.1; extra == 'cuda'
Provides-Extra: directml
Requires-Dist: onnxruntime-directml>=1.16.1; extra == 'directml'
Provides-Extra: memray
Requires-Dist: memray>=1.17.1; extra == 'memray'
